<Properties StartupConfiguration="{ABE4CEBD-87BE-0A97-95FA-B9B3B101725D}|">
  <MonoDevelop.Ide.Workbench ActiveDocument="Assets/Scripts/PlayerController.cs">
    <Files>
      <File FileName="Assets/Scripts/CameraController.cs" Line="1" Column="1" />
      <File FileName="Assets/Scripts/PlayerController.cs" Line="1" Column="1" />
    </Files>
  </MonoDevelop.Ide.Workbench>
  <MonoDevelop.Ide.DebuggingService.PinnedWatches />
  <MonoDevelop.Ide.Workspace ActiveConfiguration="Debug" />
  <MonoDevelop.Ide.ItemProperties.Assembly-CSharp PreferredExecutionTarget="59da0b7d-6aaa-49df-96d7-262bac0e966c" />
  <MonoDevelop.Ide.DebuggingService.Breakpoints>
    <BreakpointStore />
  </MonoDevelop.Ide.DebuggingService.Breakpoints>
  <MultiItemStartupConfigurations />
</Properties>